setup.py
fzysearch/__init__.py
fzysearch.egg-info/PKG-INFO
fzysearch.egg-info/SOURCES.txt
fzysearch.egg-info/dependency_links.txt
fzysearch.egg-info/not-zip-safe
fzysearch.egg-info/top_level.txt