Metadata-Version: 1.0
Name: fzysearch
Version: 0.2
Summary: fuzzy searches a string input to a list and returns results from the list in order of relevance
Home-page: http://github.com/ridwanmsharif/fzysearch
Author: Ridwan M. Sharif
Author-email: ridwanmsharif@hotmail.com
License: MIT
Platform: UNKNOWN
